setup.cfg
setup.py
bin/fixschema.py
bin/importmydata.py
dbtruck/__init__.py
dbtruck/dbtruck.py
dbtruck/infertypes.py
dbtruck/util.py
dbtruck.egg-info/PKG-INFO
dbtruck.egg-info/SOURCES.txt
dbtruck.egg-info/dependency_links.txt
dbtruck.egg-info/requires.txt
dbtruck.egg-info/top_level.txt
dbtruck/analyze/__init__.py
dbtruck/analyze/analyze.py
dbtruck/analyze/database.py
dbtruck/analyze/fuzzyjoin.py
dbtruck/analyze/geocode.py
dbtruck/analyze/hidden.py
dbtruck/analyze/load_data.py
dbtruck/analyze/location.py
dbtruck/analyze/metadata.py
dbtruck/analyze/models.py
dbtruck/exporters/__init__.py
dbtruck/exporters/base.py
dbtruck/exporters/csvmethods.py
dbtruck/exporters/db.py
dbtruck/exporters/pg.py
dbtruck/parsers/__init__.py
dbtruck/parsers/concrete.py
dbtruck/parsers/dataiter.py
dbtruck/parsers/parsers.py
dbtruck/parsers/util.py