Metadata-Version: 1.0
Name: dbtruck
Version: 0.0.13
Summary: Dump your data into your database
Home-page: http://github.com/sirrice/dbtruck
Author: Eugene Wu
Author-email: eugenewu@mit.edu
License: MIT
Keywords: library query db import
Platform: UNKNOWN
